[
  {
    "pageNum": 1,
    "sentenceNum": 1,
    "text": "Puupy Runs"
  },
  {
    "pageNum": 2,
    "sentenceNum": 1,
    "text": "Puppy runs."
  },
  {
    "pageNum": 2,
    "sentenceNum": 2,
    "text": "Through the gate."
  },
  {
    "pageNum": 2,
    "sentenceNum": 3,
    "text": "In the fence."
  },
  {
    "pageNum": 3,
    "sentenceNum": 1,
    "text": "Rush! Rush!"
  },
  {
    "pageNum": 4,
    "sentenceNum": 1,
    "text": "Puppy runs."
  },
  {
    "pageNum": 4,
    "sentenceNum": 2,
    "text": "Rush! Rush!"
  },
  {
    "pageNum": 5,
    "sentenceNum": 1,
    "text": "Through the door."
  },
  {
    "pageNum": 5,
    "sentenceNum": 2,
    "text": "Into the house."
  },
  {
    "pageNum": 6,
    "sentenceNum": 1,
    "text": "Rush! Rush!"
  },
  {
    "pageNum": 6,
    "sentenceNum": 2,
    "text": "Puppy runs."
  },
  {
    "pageNum": 7,
    "sentenceNum": 1,
    "text": "Around the lamp."
  },
  {
    "pageNum": 7,
    "sentenceNum": 2,
    "text": "Up the stairs."
  },
  {
    "pageNum": 8,
    "sentenceNum": 1,
    "text": "Puppy runs."
  },
  {
    "pageNum": 8,
    "sentenceNum": 2,
    "text": "Rush! Rush!"
  },
  {
    "pageNum": 9,
    "sentenceNum": 1,
    "text": "To the balcony."
  },
  {
    "pageNum": 9,
    "sentenceNum": 2,
    "text": "Out the window."
  },
  {
    "pageNum": 10,
    "sentenceNum": 1,
    "text": "Puppy runs."
  },
  {
    "pageNum": 10,
    "sentenceNum": 2,
    "text": "Rush! Rush!"
  },
  {
    "pageNum": 10,
    "sentenceNum": 3,
    "text": "To the garden."
  },
  {
    "pageNum": 10,
    "sentenceNum": 4,
    "text": "Into the flowers."
  },
  {
    "pageNum": 11,
    "sentenceNum": 1,
    "text": "I got it!"
  }
]